rtl/adc_model.v
`timescale 10ps/1ps

module adc_model#(
    parameter CHANNELS = 32,  // number of channels
    parameter DATAWIDTH = 8,  // resolution of adc
    parameter CALIB_CYCLES = 1, // number of calibration cycles
    parameter CALIB_TIME = 16384, // calibration time in clock cycles
    parameter GAIN_CAL_WIDTH = 8, // gain calibration data width
    parameter DESKEW_CAL_WIDTH = 8 // deskew calibration data width
)(
    input wire clk_28G, // 28G clock input
    input wire rst_n, // active low reset

    // timing control
    output reg adc_ready,   // reseting is done
    input wire calib_start, // start calibration
    output reg adc_calib_done,  // calibration done
    input wire adc_run, // start adc

    // data interface 
    output reg [DATAWIDTH*CHANNELS-1:0] adc_data, // adc data output
    output reg clk_sram, // sram clock
    output reg en_sram // sram enable
);


    reg [31:0] calib_counter; // calibration counter
    //reg [DATAWIDTH*CHANNELS-1:0] data_counter;  // counter for adc data generation
    reg [7:0] base_sample; // base sample value for adc data
    reg [7:0] next_base_sample; // next base sample value
    reg [9:0] cycle_counter; // cycle counter for calibration timing
    reg internal_en_run; // internal adc run signal
    reg [4:0] clk_div_cnt; // clock divider counter
    integer i; // for loops

    // initial
    initial begin
        // unkown state at the beginning
        adc_ready = 1'bx;
        adc_calib_done = 1'bx;
        //adc_data = {DATAWIDTH*CHANNELS{1'bx}};
        //clk_sram = 1'bx;
        //en_sram = 1'bx;
        internal_en_run = 1'bx;
        calib_counter = 32'dx;
        //data_counter = {DATAWIDTH*CHANNELS{1'bx}};
        cycle_counter = 10'dx;

        wait (rst_n == 1'b0);
        // system reset
        # 2;    // delay 2 time units
        adc_ready = 1'b0;
        adc_calib_done = 1'b0;
        //adc_data = {DATAWIDTH*CHANNELS{1'b0}};
        //clk_sram = 1'b0;
        //en_sram = 1'b0;
        calib_counter = 32'd0;
        //data_counter = {DATAWIDTH*CHANNELS{1'b0}};
        cycle_counter = 10'd0;
        internal_en_run = 1'b0;

        wait (rst_n);
        // calibration process after reset
        @(posedge clk_28G); #2  // synchronous to clk_28G
        adc_ready = 1'b1;

        wait (calib_start);
        // start calibration
        #2
        adc_ready = 1'b0; // adc is busy in calibration
        repeat (CALIB_CYCLES*CALIB_TIME) @(posedge clk_28G); // wait for calibration time
        #2
        adc_ready = 1'b1; // adc is ready
        adc_calib_done = 1'b1; // calibration done 

        wait(!adc_run);
        // wait for adc_run deassertion
        internal_en_run = 1'b1;
    end

    always @(posedge clk_28G or negedge rst_n) begin
        if (!rst_n) begin
            // reset for data and clk_sram
            adc_data <= {DATAWIDTH*CHANNELS{1'b0}};
            clk_sram <= 1'b1;
            en_sram <= 1'b0;
            //data_counter <= {DATAWIDTH*CHANNELS{1'b0}};
            clk_div_cnt <= 5'd0;
            base_sample <= 8'd0;
        end
        else if(internal_en_run) begin
            //data_counter <= data_counter +1'b1;
            //divider 
            clk_div_cnt <= clk_div_cnt + 1'b1;
            if(clk_div_cnt == 5'd31) begin
                clk_sram <= #1 1'b1;
            end
            else if(clk_div_cnt == 5'd15) begin
                clk_sram <= #1 1'b0;
            end

            if (clk_div_cnt == 5'd31) begin
                next_base_sample = base_sample + CHANNELS;   // use next_base_sample to avoid Non-blocking assignment issue
                base_sample <= next_base_sample;
                en_sram <= #0.5 1'b1;
                for (i = 0; i<CHANNELS; i = i + 1) begin
                    adc_data[i*DATAWIDTH +: DATAWIDTH] <= #1.5 (next_base_sample + i);
                end
            end
            else begin
                en_sram <= #0.5 1'b0;
            end
        end
    end

endmodule

tb/tb_adc_model.v
//`include "../rtl/adc_model.v"
`timescale 10ps/1ps
module tb_adc_model;

parameter CHANNELS = 32;
parameter DATAWIDTH = 8;
parameter CALIB_CYCLES = 1;
parameter CALIB_TIME = 64;   // shorter calibration time in clock cycles
parameter GAIN_CAL_WIDTH = 8;
parameter DESKEW_CAL_WIDTH = 8;

// input signals
reg clk_25G; //25G clock input
reg rst_n; // active low reset
reg calib_start; // start calibration
reg adc_run; // start adc

// output signals
wire adc_ready; // adc is ready
wire adc_calib_done; // calibration done
wire [DATAWIDTH*CHANNELS-1:0] adc_data; // adc data output
wire clk_sram; // sram clock
wire en_sram; // sram enable

// instantiate the adc model
adc_model #(.CHANNELS(CHANNELS),
            .DATAWIDTH(DATAWIDTH),
            .CALIB_CYCLES(CALIB_CYCLES),
            .CALIB_TIME(CALIB_TIME),
            .GAIN_CAL_WIDTH(GAIN_CAL_WIDTH),
            .DESKEW_CAL_WIDTH(DESKEW_CAL_WIDTH)
) u_adc(
    .clk_28G(clk_25G),
    .rst_n(rst_n),
    .adc_ready(adc_ready),
    .calib_start(calib_start),
    .adc_calib_done(adc_calib_done),
    .adc_run(adc_run),
    .adc_data(adc_data),
    .clk_sram(clk_sram),
    .en_sram(en_sram)
);

// clock generation
initial clk_25G = 0;
always #2 clk_25G = ~clk_25G; // 25G clock


// controller
initial begin
    rst_n = 1;
    calib_start = 0;
    adc_run = 1'b1;     // active low
    // wave file configuration
    $dumpfile("./build/tb_adc_model.vcd");
    $dumpvars(0, tb_adc_model);

    $display("=======Simulation(Clock = 25GHz)=======");
    $display("[%t] Starting Simulation...", $time);

    # 100 
    $display("[%t] Asserting reset...", $time);
    rst_n = 0;
    # 200 
    $display("[%t] Releasing reset...", $time);
    rst_n = 1;
    wait (adc_ready == 1'b1);
    $display("[%t] ADC is ready.", $time);
    @(posedge clk_25G); #2
    calib_start = 1;
    wait (adc_ready == 1'b0);
    $display("[%t] ADC is busy.", $time);
    calib_start = 0; // de-assert calib_start
    wait (adc_calib_done == 1'b1);
    $display("[%t] ADC calibration is done.", $time);
    # 400 
    $display("[%t] ADC start running...", $time);
    @(posedge clk_25G);
    adc_run = 1'b0; // start adc    
    #50000; 
    $display("[%t] Stopping Simulation...", $time);
    $display("=============End=============");
    $finish;
end

always @(posedge clk_25G) begin
    if(en_sram) begin
        $display("[%t] Data Strobe! Output: %h",$time, adc_data);
    end
end 

endmodule

build/tb_adc_model.vcd
$date
	Thu Jan 29 13:10:35 2026
$end
$version
	Icarus Verilog
$end
$timescale
	1ps
$end
$scope module tb_adc_model $end
$var wire 1 ! en_sram $end
$var wire 1 " clk_sram $end
$var wire 1 # adc_ready $end
$var wire 256 $ adc_data [255:0] $end
$var wire 1 % adc_calib_done $end
$var reg 1 & adc_run $end
$var reg 1 ' calib_start $end
$var reg 1 ( clk_25G $end
$var reg 1 ) rst_n $end
$scope module u_adc $end
$var wire 1 & adc_run $end
$var wire 1 ' calib_start $end
$var wire 1 ( clk_28G $end
$var wire 1 ) rst_n $end
$var reg 1 % adc_calib_done $end
$var reg 256 * adc_data [255:0] $end
$var reg 1 # adc_ready $end
$var reg 8 + base_sample [7:0] $end
$var reg 32 , calib_counter [31:0] $end
$var reg 5 - clk_div_cnt [4:0] $end
$var reg 1 " clk_sram $end
$var reg 10 . cycle_counter [9:0] $end
$var reg 1 ! en_sram $end
$var reg 1 / internal_en_run $end
$var reg 8 0 next_base_sample [7:0] $end
$var integer 32 1 i [31:0] $end
$upscope $end
$upscope $end
$enddefinitions $end
#0
$dumpvars
bx 1
bx 0
x/
bx .
bx -
bx ,
bx +
bx *
1)
0(
0'
1&
x%
bx $
x#
x"
x!
$end
#20
1(
#40
0(
#60
1(
#80
0(
#100
1(
#120
0(
#140
1(
#160
0(
#180
1(
#200
0(
#220
1(
#240
0(
#260
1(
#280
0(
#300
1(
#320
0(
#340
1(
#360
0(
#380
1(
#400
0(
#420
1(
#440
0(
#460
1(
#480
0(
#500
1(
#520
0(
#540
1(
#560
0(
#580
1(
#600
0(
#620
1(
#640
0(
#660
1(
#680
0(
#700
1(
#720
0(
#740
1(
#760
0(
#780
1(
#800
0(
#820
1(
#840
0(
#860
1(
#880
0(
#900
1(
#920
0(
#940
1(
#960
0(
#980
1(
#1000
b0 +
b0 -
0!
1"
b0 $
b0 *
0(
0)
#1020
0/
b0 .
b0 ,
0%
0#
1(
#1040
0(
#1060
1(
#1080
0(
#1100
1(
#1120
0(
#1140
1(
#1160
0(
#1180
1(
#1200
0(
#1220
1(
#1240
0(
#1260
1(
#1280
0(
#1300
1(
#1320
0(
#1340
1(
#1360
0(
#1380
1(
#1400
0(
#1420
1(
#1440
0(
#1460
1(
#1480
0(
#1500
1(
#1520
0(
#1540
1(
#1560
0(
#1580
1(
#1600
0(
#1620
1(
#1640
0(
#1660
1(
#1680
0(
#1700
1(
#1720
0(
#1740
1(
#1760
0(
#1780
1(
#1800
0(
#1820
1(
#1840
0(
#1860
1(
#1880
0(
#1900
1(
#1920
0(
#1940
1(
#1960
0(
#1980
1(
#2000
0(
#2020
1(
#2040
0(
#2060
1(
#2080
0(
#2100
1(
#2120
0(
#2140
1(
#2160
0(
#2180
1(
#2200
0(
#2220
1(
#2240
0(
#2260
1(
#2280
0(
#2300
1(
#2320
0(
#2340
1(
#2360
0(
#2380
1(
#2400
0(
#2420
1(
#2440
0(
#2460
1(
#2480
0(
#2500
1(
#2520
0(
#2540
1(
#2560
0(
#2580
1(
#2600
0(
#2620
1(
#2640
0(
#2660
1(
#2680
0(
#2700
1(
#2720
0(
#2740
1(
#2760
0(
#2780
1(
#2800
0(
#2820
1(
#2840
0(
#2860
1(
#2880
0(
#2900
1(
#2920
0(
#2940
1(
#2960
0(
#2980
1(
#3000
0(
1)
#3020
1(
#3040
1#
0(
#3060
1(
#3080
1'
0(
#3100
0'
0#
1(
#3120
0(
#3140
1(
#3160
0(
#3180
1(
#3200
0(
#3220
1(
#3240
0(
#3260
1(
#3280
0(
#3300
1(
#3320
0(
#3340
1(
#3360
0(
#3380
1(
#3400
0(
#3420
1(
#3440
0(
#3460
1(
#3480
0(
#3500
1(
#3520
0(
#3540
1(
#3560
0(
#3580
1(
#3600
0(
#3620
1(
#3640
0(
#3660
1(
#3680
0(
#3700
1(
#3720
0(
#3740
1(
#3760
0(
#3780
1(
#3800
0(
#3820
1(
#3840
0(
#3860
1(
#3880
0(
#3900
1(
#3920
0(
#3940
1(
#3960
0(
#3980
1(
#4000
0(
#4020
1(
#4040
0(
#4060
1(
#4080
0(
#4100
1(
#4120
0(
#4140
1(
#4160
0(
#4180
1(
#4200
0(
#4220
1(
#4240
0(
#4260
1(
#4280
0(
#4300
1(
#4320
0(
#4340
1(
#4360
0(
#4380
1(
#4400
0(
#4420
1(
#4440
0(
#4460
1(
#4480
0(
#4500
1(
#4520
0(
#4540
1(
#4560
0(
#4580
1(
#4600
0(
#4620
1(
#4640
0(
#4660
1(
#4680
0(
#4700
1(
#4720
0(
#4740
1(
#4760
0(
#4780
1(
#4800
0(
#4820
1(
#4840
0(
#4860
1(
#4880
0(
#4900
1(
#4920
0(
#4940
1(
#4960
0(
#4980
1(
#5000
0(
#5020
1(
#5040
0(
#5060
1(
#5080
0(
#5100
1(
#5120
0(
#5140
1(
#5160
0(
#5180
1(
#5200
0(
#5220
1(
#5240
0(
#5260
1(
#5280
0(
#5300
1(
#5320
0(
#5340
1(
#5360
0(
#5380
1(
#5400
0(
#5420
1(
#5440
0(
#5460
1(
#5480
0(
#5500
1(
#5520
0(
#5540
1(
#5560
0(
#5580
1(
#5600
0(
#5620
1(
#5640
0(
#5660
1(
#5680
1%
1#
0(
